semgeom/__init__.py
semgeom/biases.py
semgeom/core.py
semgeom/local_axes.py
semgeom/pairs.py
semgeom/semantic_field.py
semgeom/topic_coverage.py
semgeom/utils.py
semgeom/viz.py
semgeom-1.1.dist-info/LICENSE
semgeom-1.1.dist-info/METADATA
semgeom-1.1.dist-info/WHEEL
semgeom-1.1.dist-info/top_level.txt
semgeom-1.1.dist-info/RECORD
