Metadata-Version: 2.2
Name: semgeom
Version: 1.1
Author: Alina Topper
License: MIT
License-File: LICENSE
Requires-Dist: numpy
Requires-Dist: scipy
Requires-Dist: scikit-learn
Requires-Dist: matplotlib
Requires-Dist: pandas
Provides-Extra: viz
Requires-Dist: plotly; extra == "viz"
Requires-Dist: seaborn; extra == "viz"
Provides-Extra: models
Requires-Dist: sentence-transformers; extra == "models"
Provides-Extra: spatial
Requires-Dist: alphashape; extra == "spatial"
Requires-Dist: shapely; extra == "spatial"
Dynamic: author
Dynamic: description
Dynamic: description-content-type
Dynamic: license
Dynamic: provides-extra
Dynamic: requires-dist
